yamlett/__init__.py
yamlett/artifact.py
yamlett/tracking.py
yamlett/utils_test.py
yamlett-0.0.7.dist-info/LICENSE
yamlett-0.0.7.dist-info/WHEEL
yamlett-0.0.7.dist-info/METADATA
yamlett-0.0.7.dist-info/RECORD
