Metadata-Version: 2.1
Name: yamlett
Version: 0.0.7
Summary: Yet Another ML Experiment Tracking Tool
Home-page: https://github.com/vlandeiro/yamlett
License: MIT
Keywords: ml,machine learning,experiment tracking,mongodb
Author: Virgile Landeiro
Author-email: virgile.landeiro@gmail.com
Requires-Python: >=3.6,<4.0
Classifier: Development Status :: 3 - Alpha
Classifier: Intended Audience :: Science/Research
Classifier: License :: OSI Approved :: MIT License
Classifier: Programming Language :: Python :: 3
Classifier: Programming Language :: Python :: 3.6
Classifier: Programming Language :: Python :: 3.7
Classifier: Programming Language :: Python :: 3.8
Classifier: Programming Language :: Python :: 3.9
Classifier: Topic :: Scientific/Engineering :: Artificial Intelligence
Requires-Dist: cloudpathlib (>=0,<1)
Requires-Dist: cloudpickle (>=1.6.0,<2.0.0)
Requires-Dist: pymongo (>=3.11.1,<4.0.0)
Requires-Dist: python-box[all] (>=5.2.0,<6.0.0)
Project-URL: Repository, https://github.com/vlandeiro/yamlett
